changelog/__init__.py
changelog/changelog.css
changelog/cmd.py
changelog/docutils.py
changelog/environment.py
changelog/generate_rst.py
changelog/mdwriter.py
changelog/sphinxext.py
changelog-0.6.2.dist-info/licenses/LICENSE
changelog-0.6.2.dist-info/METADATA
changelog-0.6.2.dist-info/WHEEL
changelog-0.6.2.dist-info/entry_points.txt
changelog-0.6.2.dist-info/top_level.txt
changelog-0.6.2.dist-info/RECORD
