Metadata-Version: 2.4
Name: changelog
Version: 0.6.2
Summary: Provides simple Sphinx markup to render changelog displays.
Home-page: https://github.com/sqlalchemyorg/changelog
Author: Mike Bayer
Author-email: mike@zzzcomputing.com
License: MIT
Keywords: Sphinx
Classifier: Development Status :: 3 - Alpha
Classifier: Environment :: Console
Classifier: Intended Audience :: Developers
Classifier: Programming Language :: Python
Classifier: Programming Language :: Python :: 3
Classifier: Programming Language :: Python :: Implementation :: CPython
Classifier: Programming Language :: Python :: Implementation :: PyPy
Classifier: Topic :: Documentation
License-File: LICENSE
Requires-Dist: Sphinx>=4.0.0
Requires-Dist: docutils
Requires-Dist: looseversion
Dynamic: author
Dynamic: author-email
Dynamic: classifier
Dynamic: description
Dynamic: home-page
Dynamic: keywords
Dynamic: license
Dynamic: license-file
Dynamic: requires-dist
Dynamic: summary
